ingeniamotion/__init__.py
ingeniamotion/_utils.py
ingeniamotion/_version.py
ingeniamotion/capture.py
ingeniamotion/communication.py
ingeniamotion/configuration.py
ingeniamotion/disturbance.py
ingeniamotion/drive_tests.py
ingeniamotion/errors.py
ingeniamotion/exceptions.py
ingeniamotion/feedbacks.py
ingeniamotion/fsoe.py
ingeniamotion/homing.py
ingeniamotion/information.py
ingeniamotion/input_output.py
ingeniamotion/metaclass.py
ingeniamotion/motion.py
ingeniamotion/motion_controller.py
ingeniamotion/pdo.py
ingeniamotion/py.typed
ingeniamotion/enums/__init__.py
ingeniamotion/fsoe_master/__init__.py
ingeniamotion/fsoe_master/errors.py
ingeniamotion/fsoe_master/frame.py
ingeniamotion/fsoe_master/fsoe.py
ingeniamotion/fsoe_master/handler.py
ingeniamotion/fsoe_master/maps_validator.py
ingeniamotion/fsoe_master/parameters.py
ingeniamotion/fsoe_master/process_image.py
ingeniamotion/fsoe_master/safety_functions.py
ingeniamotion/monitoring/__init__.py
ingeniamotion/monitoring/base_monitoring.py
ingeniamotion/monitoring/monitoring_v1.py
ingeniamotion/monitoring/monitoring_v3.py
ingeniamotion/wizard_tests/__init__.py
ingeniamotion/wizard_tests/base_test.py
ingeniamotion/wizard_tests/brake.py
ingeniamotion/wizard_tests/brake_tune.py
ingeniamotion/wizard_tests/phase_calibration.py
ingeniamotion/wizard_tests/phasing_check.py
ingeniamotion/wizard_tests/sto.py
ingeniamotion/wizard_tests/stoppable.py
ingeniamotion/wizard_tests/feedbacks_tests/__init__.py
ingeniamotion/wizard_tests/feedbacks_tests/absolute_encoder1_test.py
ingeniamotion/wizard_tests/feedbacks_tests/absolute_encoder2_test.py
ingeniamotion/wizard_tests/feedbacks_tests/dc_feedback_polarity_test.py
ingeniamotion/wizard_tests/feedbacks_tests/dc_feedback_resolution_test.py
ingeniamotion/wizard_tests/feedbacks_tests/digital_hall_test.py
ingeniamotion/wizard_tests/feedbacks_tests/digital_incremental1_test.py
ingeniamotion/wizard_tests/feedbacks_tests/digital_incremental2_test.py
ingeniamotion-0.10.0.dist-info/LICENSE.md
ingeniamotion-0.10.0.dist-info/METADATA
ingeniamotion-0.10.0.dist-info/WHEEL
ingeniamotion-0.10.0.dist-info/top_level.txt
ingeniamotion-0.10.0.dist-info/RECORD
