Metadata-Version: 2.1
Name: ingeniamotion
Version: 0.10.0
Summary: Motion library for Novanta servo drives
Author-email: Novanta <support@ingeniamc.com>
Project-URL: Homepage, https://www.ingeniamc.com
Project-URL: Documentation, https://distext.ingeniamc.com/doc/ingeniamotion/latest/
Project-URL: Source, https://github.com/ingeniamc/ingeniamotion
Classifier: Programming Language :: Python :: 3
Classifier: Programming Language :: Python :: 3.9
Classifier: Programming Language :: Python :: 3.10
Classifier: Programming Language :: Python :: 3.11
Classifier: Programming Language :: Python :: 3.12
Classifier: Operating System :: OS Independent
Requires-Python: >=3.9
License-File: LICENSE.md
Requires-Dist: ingenialink<8.0.0,>=7.5.1
Requires-Dist: ingenialogger>=0.2.1
Requires-Dist: ifaddr==0.1.7
Provides-Extra: fsoe
Requires-Dist: fsoe_master==0.2.0; extra == "fsoe"
